CHANGES.txt
README.txt
bootstrap.py
buildout.cfg
setup.py
src/hurry/__init__.py
src/hurry.qunit.egg-info/PKG-INFO
src/hurry.qunit.egg-info/SOURCES.txt
src/hurry.qunit.egg-info/dependency_links.txt
src/hurry.qunit.egg-info/entry_points.txt
src/hurry.qunit.egg-info/namespace_packages.txt
src/hurry.qunit.egg-info/not-zip-safe
src/hurry.qunit.egg-info/requires.txt
src/hurry.qunit.egg-info/top_level.txt
src/hurry/qunit/__init__.py
src/hurry/qunit/_lib.py
src/hurry/qunit/qunit.txt
src/hurry/qunit/tests.py
src/hurry/qunit/qunit-build/qunit.css
src/hurry/qunit/qunit-build/qunit.js