Metadata-Version: 1.0
Name: hurry.qunit
Version: 0.5
Summary: Hurry resource for JQuery Qunit
Home-page: http://pypi.python.org/pypi/hurry.qunit
Author: Izhar Firdaus / Martijn Faassen
Author-email: faassen@startifact.com
License: MIT / GPL
Platform: UNKNOWN
Classifier: Programming Language :: Python
Classifier: Topic :: Software Development :: Libraries :: Python Modules
